fibrous_limit_order/__init__.py
fibrous_limit_order/src/__init__.py
fibrous_limit_order/src/examples/__init__.py
fibrous_limit_order/src/examples/cancel_order.py
fibrous_limit_order/src/examples/fill_order.py
fibrous_limit_order/src/examples/full_create_order.py
fibrous_limit_order/src/examples/full_fill_order.py
fibrous_limit_order/src/examples/get_nonce.py
fibrous_limit_order/src/examples/get_orders.py
fibrous_limit_order/src/examples/get_remaining_amount.py
fibrous_limit_order/src/examples/place_order.py
fibrous_limit_order/src/examples/sign_message.py
fibrous_limit_order/src/limit_order/__init__.py
fibrous_limit_order/src/limit_order/accounts.py
fibrous_limit_order/src/limit_order/constants.py
fibrous_limit_order/src/limit_order/limit_order.py
fibrous_limit_order/src/limit_order/message_sign.py
fibrous_limit_order/src/limit_order/mock_data.py
fibrous_limit_order/src/limit_order/order_types.py
fibrous_limit_order/src/limit_order/personal_data.py
fibrous_limit_order/src/limit_order/types.py
fibrous_limit_order/src/limit_order/utils.py
fibrous_limit_order/src/tokens.json
fibrous_limit_order-1.0.0.dist-info/LICENCE
fibrous_limit_order-1.0.0.dist-info/METADATA
fibrous_limit_order-1.0.0.dist-info/WHEEL
fibrous_limit_order-1.0.0.dist-info/RECORD
