Metadata-Version: 2.1
Name: fibrous_limit_order
Version: 1.0.0
Summary: A Python SDK for Fibrous Finance Limit Order
License: MIT
Author: zeroonesymphony
Author-email: kermo@fibrous.finance
Requires-Python: >=3.9,<3.13
Classifier: License :: OSI Approved :: MIT License
Classifier: Programming Language :: Python :: 3
Classifier: Programming Language :: Python :: 3.9
Classifier: Programming Language :: Python :: 3.10
Classifier: Programming Language :: Python :: 3.11
Classifier: Programming Language :: Python :: 3.12
